aiopygismeteo/__init__.py
aiopygismeteo/_gismeteo.py
aiopygismeteo/_http.py
aiopygismeteo/py.typed
aiopygismeteo/types.py
aiopygismeteo/_endpoints/__init__.py
aiopygismeteo/_endpoints/current.py
aiopygismeteo/_endpoints/search.py
aiopygismeteo/_endpoints/step24.py
aiopygismeteo/_endpoints/step3.py
aiopygismeteo/_endpoints/step6.py
aiopygismeteo-7.0.2.dist-info/METADATA
aiopygismeteo-7.0.2.dist-info/WHEEL
aiopygismeteo-7.0.2.dist-info/licenses/LICENSE
aiopygismeteo-7.0.2.dist-info/RECORD
